goodtypes/__init__.py
goodtypes/__pkginfo__.py
goodtypes/bytes.py
goodtypes/daterange.py
goodtypes/util.py
tests/__init__.py
tests/test_bytes.py
tests/test_daterange.py
tests/test_util.py
goodtypes-0.2.0.dist-info/LICENSE
goodtypes-0.2.0.dist-info/METADATA
goodtypes-0.2.0.dist-info/WHEEL
goodtypes-0.2.0.dist-info/top_level.txt
goodtypes-0.2.0.dist-info/RECORD
