Metadata-Version: 2.1
Name: goodtypes
Version: 0.2.0
Summary: Good Datatypes
Home-page: https://github.com/scravy/the-good-type
Author: Julian Fleischer
Author-email: tirednesscankill@warhog.net
License: UNKNOWN
Platform: UNKNOWN
Classifier: Programming Language :: Python :: 3
Classifier: License :: OSI Approved :: MIT License
Classifier: Operating System :: OS Independent
Requires-Python: >=3.7
